pinit/__init__.py
pinit/cli.py
pinit/extractor.py
pinit/pinboard_client.py
smartpin-0.2.4.dist-info/METADATA
smartpin-0.2.4.dist-info/WHEEL
smartpin-0.2.4.dist-info/entry_points.txt
smartpin-0.2.4.dist-info/licenses/LICENSE
smartpin-0.2.4.dist-info/RECORD
