Metadata-Version: 2.4
Name: smartpin
Version: 0.2.4
Summary: AI-powered Pinboard bookmark manager using AI for tagging and summarization
Project-URL: Homepage, https://github.com/kevinmcmahon/smartpin
Project-URL: Repository, https://github.com/kevinmcmahon/smartpin
Project-URL: Issues, https://github.com/kevinmcmahon/smartpin/issues
Author-email: Kevin McMahon <kevinmcmahon@users.noreply.github.com>
License: Apache-2.0
License-File: LICENSE
Keywords: ai,bookmarks,cli,pinboard,tagging
Classifier: Development Status :: 4 - Beta
Classifier: Environment :: Console
Classifier: Intended Audience :: End Users/Desktop
Classifier: License :: OSI Approved :: Apache Software License
Classifier: Operating System :: OS Independent
Classifier: Programming Language :: Python :: 3
Classifier: Programming Language :: Python :: 3.11
Classifier: Programming Language :: Python :: 3.12
Classifier: Programming Language :: Python :: 3.13
Classifier: Topic :: Internet :: WWW/HTTP
Classifier: Topic :: Utilities
Requires-Python: >=3.11
Requires-Dist: beautifulsoup4>=4.13.4
Requires-Dist: click>=8.2.1
Requires-Dist: httpx>=0.28.1
Requires-Dist: jinja2>=3.1.6
Requires-Dist: llm-anthropic>=0.16
Requires-Dist: llm>=0.25
Requires-Dist: pinboard-tools
Requires-Dist: pinboard>=2.1.9
Requires-Dist: python-dotenv>=1.1.0
Requires-Dist: rich>=14.0.0
